license.txt
setup.py
PythonBadeModuleImports/PythonBadeModuleImports.py
PythonBadeModuleImports/__init__.py
PythonBadeModuleImports.egg-info/PKG-INFO
PythonBadeModuleImports.egg-info/SOURCES.txt
PythonBadeModuleImports.egg-info/dependency_links.txt
PythonBadeModuleImports.egg-info/top_level.txt